build/lib/origo/sdk/__init__.py
build/lib/origo/sdk/config.py
build/lib/origo/sdk/exceptions.py
build/lib/origo/sdk/file_cache.py
build/lib/origo/sdk/io_utils.py
build/lib/origo/sdk/sdk.py
build/lib/origo/sdk/auth/__init__.py
build/lib/origo/sdk/auth/auth.py
build/lib/origo/sdk/auth/util.py
build/lib/origo/sdk/auth/credentials/__init__.py
build/lib/origo/sdk/auth/credentials/client_credentials.py
build/lib/origo/sdk/auth/credentials/common.py
build/lib/origo/sdk/auth/credentials/password_grant.py
build/lib/origo/sdk/data/__init__.py
build/lib/origo/sdk/data/dataset.py
build/lib/origo/sdk/data/download.py
build/lib/origo/sdk/data/upload.py
build/lib/origo/sdk/dataset_authorizer/__init__.py
build/lib/origo/sdk/dataset_authorizer/simple_dataset_authorizer_client.py
build/lib/origo/sdk/elasticsearch/__init__.py
build/lib/origo/sdk/elasticsearch/queries.py
build/lib/origo/sdk/event/__init__.py
build/lib/origo/sdk/event/event_stream_client.py
build/lib/origo/sdk/event/post_event.py
build/lib/origo/sdk/pipelines/__init__.py
build/lib/origo/sdk/pipelines/client.py
build/lib/origo/sdk/pipelines/resources/__init__.py
build/lib/origo/sdk/pipelines/resources/pipeline.py
build/lib/origo/sdk/pipelines/resources/pipeline_base.py
build/lib/origo/sdk/pipelines/resources/pipeline_input.py
build/lib/origo/sdk/pipelines/resources/pipeline_instance.py
build/lib/origo/sdk/pipelines/resources/schema.py
build/lib/origo/sdk/status/__init__.py
build/lib/origo/sdk/status/status.py
origo/sdk/__init__.py
origo/sdk/config.py
origo/sdk/exceptions.py
origo/sdk/file_cache.py
origo/sdk/io_utils.py
origo/sdk/sdk.py
origo/sdk/auth/__init__.py
origo/sdk/auth/auth.py
origo/sdk/auth/util.py
origo/sdk/auth/credentials/__init__.py
origo/sdk/auth/credentials/client_credentials.py
origo/sdk/auth/credentials/common.py
origo/sdk/auth/credentials/password_grant.py
origo/sdk/data/__init__.py
origo/sdk/data/dataset.py
origo/sdk/data/download.py
origo/sdk/data/upload.py
origo/sdk/dataset_authorizer/__init__.py
origo_sdk-0.4.1.dist-info/LICENSE
origo_sdk-0.4.1.dist-info/METADATA
origo_sdk-0.4.1.dist-info/WHEEL
origo_sdk-0.4.1.dist-info/top_level.txt
origo_sdk-0.4.1.dist-info/RECORD
